<?xml version="1.0" encoding="utf-8" ?>
<dwsync>
<file name="rachel.jpg" local="128157883050156250" remote="128157622200000000" testing="0" />
<file name="cast_rachealb.gif" local="128150105492968750" remote="128157622200000000" testing="0" />
<file name="adrian.jpg" local="128157883722343750" remote="128157621600000000" testing="0" />
<file name="cast_adrianw.gif" local="128150105576250000" remote="128157621600000000" testing="0" />
<file name="ivania.jpg" local="128157884636250000" remote="128157622200000000" testing="0" />
<file name="cast_ivaniae.gif" local="128150107098281250" remote="128157621600000000" testing="0" />
<file name="ben.jpg" local="128157883265781250" remote="128157621600000000" testing="0" />
<file name="cast_bena.gif" local="128150105700000000" remote="128157621600000000" testing="0" />
<file name="arin.jpg" local="128157883916562500" remote="128157621600000000" testing="0" />
<file name="cast_arina.gif" local="128150107261093750" remote="128157621600000000" testing="0" />
<file name="matt.jpg" local="128157884139843750" remote="128157622200000000" testing="0" />
<file name="cast_mattc.gif" local="128150107496562500" remote="128157622200000000" testing="0" />
<file name="cast_johnh.gif" local="128150107764531250" remote="128157622200000000" testing="0" />
<file name="cast_clive.gif" local="128150108014062500" remote="128157621600000000" testing="0" />
<file name="cast_steveo.gif" local="128150105980937500" remote="128157622200000000" testing="0" />
<file name="cast_katec.gif" local="128150106028281250" remote="128157622200000000" testing="0" />
<file name="placeholder.jpg" local="128150110870937500" remote="128157622200000000" testing="0" />
</dwsync>